{
  "$type": "Jarditech.Models.MachinCollection, Jarditech",
  "$values": [
    {
      "$type": "Jarditech.Models.TailleHaie, Jarditech",
      "IdMachine": 15,
      "ConstructeurMachine": "reno",
      "ReferenceMachine": "123456",
      "DepoDate": "2022-03-29T15:00:45.60016+02:00",
      "RetraitDate": "2022-04-12T15:00:45.60016+02:00",
      "ClientName": "toto",
      "DescriptionClient": "problem",
      "WorkDescription": "lol",
      "Entretenir": true,
      "Repar": true,
      "Price": 15.99,
      "WorkTime": 60
    },
    {
      "$type": "Jarditech.Models.Tondeuse, Jarditech",
      "IdMachine": 2,
      "ConstructeurMachine": "MLDrrcc",
      "ReferenceMachine": "MLD00001",
      "DepoDate": "2022-03-29T15:00:45.6305873+02:00",
      "RetraitDate": "2022-04-12T15:00:45.6305873+02:00",
      "ClientName": null,
      "DescriptionClient": "problemme de battrie ",
      "WorkDescription": null,
      "Entretenir": false,
      "Repar": false,
      "Price": 0.0,
      "WorkTime": 0
    },
    {
      "$type": "Jarditech.Models.Tondeuse, Jarditech",
      "IdMachine": 3,
      "ConstructeurMachine": "labole",
      "ReferenceMachine": "TB00175HHT",
      "DepoDate": "2022-03-29T15:00:45.6409463+02:00",
      "RetraitDate": "2022-04-12T15:00:45.6409463+02:00",
      "ClientName": null,
      "DescriptionClient": null,
      "WorkDescription": null,
      "Entretenir": false,
      "Repar": false,
      "Price": 0.0,
      "WorkTime": 0
    }
  ]
}